{
  "name": {
    "ar": "جامعة صحار",
    "en": "Sohar University"
  },
  "location": {
    "city": "صحار",
    "address": "ص.ب 44، رمز بريدي 311، صحار، سلطنة عمان",
    "coordinates": {
      "latitude": 24.347328,
      "longitude": 56.707313
    }
  },
  "contact": {
    "phone": "+968 26850100",
    "fax": "+968 26720102",
    "email": "info@soharuni.edu.om",
    "website": "https://www.soharuni.edu.om"
  },
  "about": {
    "brief": "جامعة صحار هي مؤسسة تعليمية خاصة تأسست في عام 2001 في مدينة صحار بسلطنة عمان. تقدم الجامعة مجموعة متنوعة من البرامج الأكاديمية على مستوى البكالوريوس والماجستير.",
    "vision": "جامعة صحار تسعى لتكون مؤسسة تعليمية رائدة ومعترف بها دولياً تقدم تعليماً عالي الجودة وبحثاً علمياً متميزاً.",
    "mission": "توفير تعليم عالي الجودة وتطوير الأبحاث العلمية لخدمة المجتمع وتلبية احتياجات سوق العمل، مع التركيز على الابتكار والتفكير النقدي."
  },
  "accreditation": {
    "national": ["الهيئة العمانية للاعتماد الأكاديمي وضمان جودة التعليم"],
    "international": ["هيئة ضمان الجودة البريطانية (QAA)", "مجلس الاعتماد للهندسة والتكنولوجيا (ABET)"]
  },
  "partnerships": [
    {
      "name": "جامعة كوينزلاند للتكنولوجيا",
      "country": "أستراليا",
      "programs": ["تجارة", "هندسة", "علوم حاسوب"]
    },
    {
      "name": "جامعة ستيرلنغ",
      "country": "المملكة المتحدة",
      "programs": ["إدارة أعمال", "تربية"]
    },
    {
      "name": "كلية دندي للعلوم والتكنولوجيا",
      "country": "المملكة المتحدة",
      "programs": ["هندسة", "علوم حاسوب"]
    }
  ],
  "faculties": [
    {
      "name": "كلية إدارة الأعمال",
      "programs": ["إدارة الأعمال", "المحاسبة", "التسويق", "نظم المعلومات الإدارية"]
    },
    {
      "name": "كلية الهندسة",
      "programs": ["الهندسة المدنية", "الهندسة الكهربائية", "الهندسة الميكانيكية", "الهندسة الكيميائية"]
    },
    {
      "name": "كلية الحوسبة وتقنية المعلومات",
      "programs": ["علوم الحاسوب", "نظم المعلومات", "شبكات الحاسوب", "أمن المعلومات"]
    },
    {
      "name": "كلية التربية والآداب",
      "programs": ["اللغة الإنجليزية", "الترجمة", "العلوم التربوية"]
    },
    {
      "name": "كلية القانون",
      "programs": ["القانون الخاص", "القانون العام"]
    }
  ],
  "facilities": {
    "academic": ["مكتبة الجامعة", "مختبرات الحاسوب", "مختبرات الهندسة والعلوم", "قاعات دراسية حديثة"],
    "student_services": ["مركز الإرشاد الطلابي", "عيادة طبية", "صالة رياضية", "مطاعم ومقاهي"],
    "research": ["مركز البحوث والدراسات", "مركز الابتكار وريادة الأعمال"]
  },
  "programs": {
    "foundation": {
      "description": "البرنامج التأسيسي",
      "duration": "1 سنة",
      "details": "برنامج تمهيدي لتأهيل الطلاب للدراسة الجامعية، يشمل اللغة الإنجليزية والرياضيات وتقنية المعلومات"
    },
    "undergraduate": [
      {
        "name": "بكالوريوس إدارة الأعمال",
        "specializations": ["إدارة عامة", "محاسبة", "تسويق", "نظم معلومات إدارية"],
        "duration": "4 سنوات"
      },
      {
        "name": "بكالوريوس الهندسة",
        "specializations": ["هندسة مدنية", "هندسة كهربائية", "هندسة ميكانيكية", "هندسة كيميائية"],
        "duration": "4 سنوات"
      },
      {
        "name": "بكالوريوس علوم الحاسوب",
        "specializations": ["علوم الحاسوب", "نظم المعلومات", "شبكات الحاسوب", "أمن المعلومات"],
        "duration": "4 سنوات"
      },
      {
        "name": "بكالوريوس اللغة الإنجليزية",
        "specializations": ["لغويات", "أدب", "ترجمة"],
        "duration": "4 سنوات"
      },
      {
        "name": "بكالوريوس القانون",
        "specializations": ["قانون خاص", "قانون عام"],
        "duration": "4 سنوات"
      }
    ],
    "postgraduate": [
      {
        "name": "ماجستير إدارة الأعمال",
        "specializations": ["إدارة عامة", "تسويق", "مالية"],
        "duration": "2 سنوات (دوام جزئي)"
      },
      {
        "name": "ماجستير العلوم في الهندسة",
        "specializations": ["هندسة مدنية", "هندسة كهربائية", "هندسة ميكانيكية"],
        "duration": "2 سنوات"
      },
      {
        "name": "ماجستير العلوم في تكنولوجيا المعلومات",
        "specializations": ["أمن المعلومات", "تطوير البرمجيات", "علوم البيانات"],
        "duration": "2 سنوات"
      },
      {
        "name": "ماجستير التربية",
        "specializations": ["مناهج وطرق تدريس", "إدارة تربوية"],
        "duration": "2 سنوات"
      }
    ]
  },
  "admission": {
    "requirements": {
      "foundation": "شهادة دبلوم التعليم العام أو ما يعادلها بمعدل لا يقل عن 65%",
      "undergraduate": "اجتياز البرنامج التأسيسي أو اجتياز اختبار تحديد المستوى",
      "postgraduate": "شهادة البكالوريوس في تخصص ذي صلة بمعدل لا يقل عن 2.5 من 4.0"
    },
    "documents": [
      "شهادات التعليم السابقة",
      "كشف الدرجات",
      "صورة من جواز السفر أو البطاقة الشخصية",
      "صور شخصية حديثة",
      "شهادة اللغة الإنجليزية (للدراسات العليا)"
    ],
    "deadlines": {
      "fall_semester": "31 أغسطس",
      "spring_semester": "31 ديسمبر"
    }
  },
  "academic_calendar": {
    "semesters": [
      {
        "name": "الفصل الخريفي",
        "start": "سبتمبر",
        "end": "يناير"
      },
      {
        "name": "الفصل الربيعي",
        "start": "فبراير",
        "end": "يونيو"
      },
      {
        "name": "الفصل الصيفي (اختياري)",
        "start": "يوليو",
        "end": "أغسطس"
      }
    ],
    "holidays": [
      "عيد الفطر",
      "عيد الأضحى",
      "العيد الوطني العماني",
      "رأس السنة الهجرية"
    ]
  },
  "student_life": {
    "clubs": ["نادي الأعمال", "نادي الهندسة", "نادي اللغات", "النادي الثقافي", "النادي الرياضي"],
    "events": ["ملتقى الخريجين", "يوم المهنة", "المسابقات الطلابية", "المعارض العلمية"],
    "support_services": ["الإرشاد الأكاديمي", "الدعم النفسي", "التوجيه المهني", "خدمات ذوي الاحتياجات الخاصة"]
  },
  "career_services": {
    "internships": "برنامج التدريب العملي الإلزامي لطلبة السنة النهائية",
    "job_placement": "مكتب التوظيف وعلاقات الخريجين",
    "alumni_network": "رابطة خريجي جامعة صحار",
    "employers": ["شركة فالي عمان", "بنك صحار الدولي", "أوكتال", "شركة عمان للتعدين"]
  },
  "campus_life": {
    "housing": "توفر الجامعة سكناً طلابياً قريباً من الحرم الجامعي للطلاب والطالبات",
    "transportation": "خدمة الحافلات من وإلى مناطق مختلفة في صحار والمناطق المحيطة",
    "dining": "كافتيريا الجامعة ومجموعة من المطاعم والمقاهي داخل الحرم الجامعي"
  },
  "faq": [
    {
      "question": "ما هي تكلفة الدراسة في جامعة صحار؟",
      "answer": "تختلف الرسوم الدراسية حسب التخصص، وتتراوح بين 2600-3200 ريال عماني سنوياً للبرامج الجامعية، وحوالي 4000-4500 ريال عماني إجمالاً لبرامج الماجستير."
    },
    {
      "question": "هل تقدم الجامعة منحاً دراسية؟",
      "answer": "نعم، تقدم الجامعة منحاً دراسية للطلبة المتفوقين (20-50%)، ومنح للأشقاء (10%)، ومساعدات مالية للحالات المستحقة (15-30%)."
    },
    {
      "question": "هل شهادات جامعة صحار معترف بها دولياً؟",
      "answer": "نعم، جامعة صحار معتمدة من الهيئة العمانية للاعتماد الأكاديمي، ولها شراكات مع جامعات دولية مرموقة، وتحظى برامجها باعتراف دولي."
    },
    {
      "question": "هل يمكن التحويل من جامعة أخرى إلى جامعة صحار؟",
      "answer": "نعم، يمكن التحويل من جامعات أخرى مع إمكانية معادلة بعض المقررات الدراسية، شرط أن تكون من مؤسسة معترف بها وبمعدل لا يقل عن 2.0 من 4.0."
    }
  ]
} 